[
  { "id":1, "nombre":"Fundación Patitas Felices", "ciudad":"Medellín", "email":"contacto@patitas.org", "instagram":"https://instagram.com/patitas", "enfoque":"rescate", "descripcion":"Rescate y rehabilitación con enfoque positivo." },
  { "id":2, "nombre":"Club Canino Laureles", "ciudad":"Medellín", "email":"info@clublaureles.co", "instagram":"https://instagram.com/clublaureles", "enfoque":"deporte", "descripcion":"Deporte canino y socialización." },
  { "id":3, "nombre":"Adopta con Amor", "ciudad":"Envigado", "email":"hola@adoptaamor.co", "instagram":"https://instagram.com/adoptaamor", "enfoque":"rescate", "descripcion":"Adopciones responsables." },
  { "id":4, "nombre":"Escuela Canina Positiva", "ciudad":"Bello", "email":"escuela@positiva.co", "instagram":"https://instagram.com/escuelacanina", "enfoque":"educacion", "descripcion":"Educación amable y basada en refuerzo." },
  { "id":5, "nombre":"Manada Sabaneta", "ciudad":"Sabaneta", "email":"manada@sabaneta.co", "instagram":"https://instagram.com/manadasabaneta", "enfoque":"comunidad", "descripcion":"Paseos grupales y guías de bienestar." },
  { "id":6, "nombre":"Guardianes de la Calle", "ciudad":"Medellín", "email":"team@guardianes.co", "instagram":"https://instagram.com/guardianes", "enfoque":"rescate", "descripcion":"Esterilización y rescate urbano." },
  { "id":7, "nombre":"Pitbulls con Amor", "ciudad":"Itagüí", "email":"hola@pitbulls.co", "instagram":"https://instagram.com/pitbullsconamor", "enfoque":"comunidad", "descripcion":"Charlas anti-estigma y adopción." },
  { "id":8, "nombre":"Parche Canino Norte", "ciudad":"Medellín", "email":"parche@norte.co", "instagram":"https://instagram.com/parchenorte", "enfoque":"comunidad", "descripcion":"Parches y socialización en el norte." },
  { "id":9, "nombre":"Escuadrón de Bienestar", "ciudad":"Copacabana", "email":"bienestar@escuadron.co", "instagram":"https://instagram.com/escuadronbienestar", "enfoque":"educacion", "descripcion":"Talleres a familias." },
  { "id":10, "nombre":"Amigos de Cuatro Patas", "ciudad":"La Estrella", "email":"hola@4patas.co", "instagram":"https://instagram.com/4patas", "enfoque":"rescate", "descripcion":"Red de hogares de paso." }
]
